{
  "class_names": [
    "About",
    "BackgroundImageFile",
    "BackgroundImageFile1",
    "Capabilities",
    "Capabilities1",
    "Capabilities2",
    "Change",
    "ChangeList",
    "Channel",
    "Comment",
    "CommentList",
    "ContentHints",
    "ContentRestriction",
    "Corpus",
    "Drive",
    "DriveAboutGetParametersQuery",
    "DriveChangesGetStartPageTokenParametersQuery",
    "DriveChangesListParametersQuery",
    "DriveChangesWatchParametersQuery",
    "DriveChannelsStopParametersQuery",
    "DriveCommentsCreateParametersQuery",
    "DriveCommentsDeleteParametersQuery",
    "DriveCommentsGetParametersQuery",
    "DriveCommentsListParametersQuery",
    "DriveCommentsUpdateParametersQuery",
    "DriveDrivesCreateParametersQuery",
    "DriveDrivesDeleteParametersQuery",
    "DriveDrivesGetParametersQuery",
    "DriveDrivesHideParametersQuery",
    "DriveDrivesListParametersQuery",
    "DriveDrivesUnhideParametersQuery",
    "DriveDrivesUpdateParametersQuery",
    "DriveFilesCopyParametersQuery",
    "DriveFilesCreateParametersQuery",
    "DriveFilesDeleteParametersQuery",
    "DriveFilesEmptyTrashParametersQuery",
    "DriveFilesExportParametersQuery",
    "DriveFilesGenerateIdsParametersQuery",
    "DriveFilesGetParametersQuery",
    "DriveFilesListLabelsParametersQuery",
    "DriveFilesListParametersQuery",
    "DriveFilesModifyLabelsParametersQuery",
    "DriveFilesUpdateParametersQuery",
    "DriveFilesWatchParametersQuery",
    "DriveList",
    "DrivePermissionsCreateParametersQuery",
    "DrivePermissionsDeleteParametersQuery",
    "DrivePermissionsGetParametersQuery",
    "DrivePermissionsListParametersQuery",
    "DrivePermissionsUpdateParametersQuery",
    "DriveRepliesCreateParametersQuery",
    "DriveRepliesDeleteParametersQuery",
    "DriveRepliesGetParametersQuery",
    "DriveRepliesListParametersQuery",
    "DriveRepliesUpdateParametersQuery",
    "DriveRevisionsDeleteParametersQuery",
    "DriveRevisionsGetParametersQuery",
    "DriveRevisionsListParametersQuery",
    "DriveRevisionsUpdateParametersQuery",
    "DriveTeamdrivesCreateParametersQuery",
    "DriveTeamdrivesDeleteParametersQuery",
    "DriveTeamdrivesGetParametersQuery",
    "DriveTeamdrivesListParametersQuery",
    "DriveTeamdrivesUpdateParametersQuery",
    "DriveTheme",
    "File",
    "FileList",
    "GeneratedIds",
    "ImageMediaMetadata",
    "Label",
    "LabelField",
    "LabelFieldModification",
    "LabelInfo",
    "LabelList",
    "LabelModification",
    "LinkShareMetadata",
    "Location",
    "ModifyLabelsRequest",
    "ModifyLabelsResponse",
    "Permission",
    "PermissionDetail",
    "PermissionList",
    "QuotedFileContent",
    "Reply",
    "ReplyList",
    "Restrictions",
    "Restrictions1",
    "Revision",
    "RevisionList",
    "ShortcutDetails",
    "StartPageToken",
    "StorageQuota",
    "TeamDrive",
    "TeamDriveList",
    "TeamDrivePermissionDetail",
    "TeamDriveTheme",
    "Thumbnail",
    "User",
    "VideoMediaMetadata"
  ],
  "module_path": "lemma_connectors.google_drive.generated.pydantic_models",
  "operations": {
    "drive_about_get": {
      "header_parameters": null,
      "path_parameters": null,
      "query_parameters": "DriveAboutGetParametersQuery",
      "request": null,
      "response": null
    },
    "drive_changes_get_start_page_token": {
      "header_parameters": null,
      "path_parameters": null,
      "query_parameters": "DriveChangesGetStartPageTokenParametersQuery",
      "request": null,
      "response": null
    },
    "drive_changes_list": {
      "header_parameters": null,
      "path_parameters": null,
      "query_parameters": "DriveChangesListParametersQuery",
      "request": null,
      "response": null
    },
    "drive_changes_watch": {
      "header_parameters": null,
      "path_parameters": null,
      "query_parameters": "DriveChangesWatchParametersQuery",
      "request": null,
      "response": null
    },
    "drive_channels_stop": {
      "header_parameters": null,
      "path_parameters": null,
      "query_parameters": "DriveChannelsStopParametersQuery",
      "request": null,
      "response": null
    },
    "drive_comments_create": {
      "header_parameters": null,
      "path_parameters": null,
      "query_parameters": "DriveCommentsCreateParametersQuery",
      "request": null,
      "response": null
    },
    "drive_comments_delete": {
      "header_parameters": null,
      "path_parameters": null,
      "query_parameters": "DriveCommentsDeleteParametersQuery",
      "request": null,
      "response": null
    },
    "drive_comments_get": {
      "header_parameters": null,
      "path_parameters": null,
      "query_parameters": "DriveCommentsGetParametersQuery",
      "request": null,
      "response": null
    },
    "drive_comments_list": {
      "header_parameters": null,
      "path_parameters": null,
      "query_parameters": "DriveCommentsListParametersQuery",
      "request": null,
      "response": null
    },
    "drive_comments_update": {
      "header_parameters": null,
      "path_parameters": null,
      "query_parameters": "DriveCommentsUpdateParametersQuery",
      "request": null,
      "response": null
    },
    "drive_drives_create": {
      "header_parameters": null,
      "path_parameters": null,
      "query_parameters": "DriveDrivesCreateParametersQuery",
      "request": null,
      "response": null
    },
    "drive_drives_delete": {
      "header_parameters": null,
      "path_parameters": null,
      "query_parameters": "DriveDrivesDeleteParametersQuery",
      "request": null,
      "response": null
    },
    "drive_drives_get": {
      "header_parameters": null,
      "path_parameters": null,
      "query_parameters": "DriveDrivesGetParametersQuery",
      "request": null,
      "response": null
    },
    "drive_drives_hide": {
      "header_parameters": null,
      "path_parameters": null,
      "query_parameters": "DriveDrivesHideParametersQuery",
      "request": null,
      "response": null
    },
    "drive_drives_list": {
      "header_parameters": null,
      "path_parameters": null,
      "query_parameters": "DriveDrivesListParametersQuery",
      "request": null,
      "response": null
    },
    "drive_drives_unhide": {
      "header_parameters": null,
      "path_parameters": null,
      "query_parameters": "DriveDrivesUnhideParametersQuery",
      "request": null,
      "response": null
    },
    "drive_drives_update": {
      "header_parameters": null,
      "path_parameters": null,
      "query_parameters": "DriveDrivesUpdateParametersQuery",
      "request": null,
      "response": null
    },
    "drive_files_copy": {
      "header_parameters": null,
      "path_parameters": null,
      "query_parameters": "DriveFilesCopyParametersQuery",
      "request": null,
      "response": null
    },
    "drive_files_create": {
      "header_parameters": null,
      "path_parameters": null,
      "query_parameters": "DriveFilesCreateParametersQuery",
      "request": null,
      "response": null
    },
    "drive_files_delete": {
      "header_parameters": null,
      "path_parameters": null,
      "query_parameters": "DriveFilesDeleteParametersQuery",
      "request": null,
      "response": null
    },
    "drive_files_empty_trash": {
      "header_parameters": null,
      "path_parameters": null,
      "query_parameters": "DriveFilesEmptyTrashParametersQuery",
      "request": null,
      "response": null
    },
    "drive_files_export": {
      "header_parameters": null,
      "path_parameters": null,
      "query_parameters": "DriveFilesExportParametersQuery",
      "request": null,
      "response": null
    },
    "drive_files_generate_ids": {
      "header_parameters": null,
      "path_parameters": null,
      "query_parameters": "DriveFilesGenerateIdsParametersQuery",
      "request": null,
      "response": null
    },
    "drive_files_get": {
      "header_parameters": null,
      "path_parameters": null,
      "query_parameters": "DriveFilesGetParametersQuery",
      "request": null,
      "response": null
    },
    "drive_files_list": {
      "header_parameters": null,
      "path_parameters": null,
      "query_parameters": "DriveFilesListParametersQuery",
      "request": null,
      "response": null
    },
    "drive_files_list_labels": {
      "header_parameters": null,
      "path_parameters": null,
      "query_parameters": "DriveFilesListLabelsParametersQuery",
      "request": null,
      "response": null
    },
    "drive_files_modify_labels": {
      "header_parameters": null,
      "path_parameters": null,
      "query_parameters": "DriveFilesModifyLabelsParametersQuery",
      "request": null,
      "response": null
    },
    "drive_files_update": {
      "header_parameters": null,
      "path_parameters": null,
      "query_parameters": "DriveFilesUpdateParametersQuery",
      "request": null,
      "response": null
    },
    "drive_files_watch": {
      "header_parameters": null,
      "path_parameters": null,
      "query_parameters": "DriveFilesWatchParametersQuery",
      "request": null,
      "response": null
    },
    "drive_permissions_create": {
      "header_parameters": null,
      "path_parameters": null,
      "query_parameters": "DrivePermissionsCreateParametersQuery",
      "request": null,
      "response": null
    },
    "drive_permissions_delete": {
      "header_parameters": null,
      "path_parameters": null,
      "query_parameters": "DrivePermissionsDeleteParametersQuery",
      "request": null,
      "response": null
    },
    "drive_permissions_get": {
      "header_parameters": null,
      "path_parameters": null,
      "query_parameters": "DrivePermissionsGetParametersQuery",
      "request": null,
      "response": null
    },
    "drive_permissions_list": {
      "header_parameters": null,
      "path_parameters": null,
      "query_parameters": "DrivePermissionsListParametersQuery",
      "request": null,
      "response": null
    },
    "drive_permissions_update": {
      "header_parameters": null,
      "path_parameters": null,
      "query_parameters": "DrivePermissionsUpdateParametersQuery",
      "request": null,
      "response": null
    },
    "drive_replies_create": {
      "header_parameters": null,
      "path_parameters": null,
      "query_parameters": "DriveRepliesCreateParametersQuery",
      "request": null,
      "response": null
    },
    "drive_replies_delete": {
      "header_parameters": null,
      "path_parameters": null,
      "query_parameters": "DriveRepliesDeleteParametersQuery",
      "request": null,
      "response": null
    },
    "drive_replies_get": {
      "header_parameters": null,
      "path_parameters": null,
      "query_parameters": "DriveRepliesGetParametersQuery",
      "request": null,
      "response": null
    },
    "drive_replies_list": {
      "header_parameters": null,
      "path_parameters": null,
      "query_parameters": "DriveRepliesListParametersQuery",
      "request": null,
      "response": null
    },
    "drive_replies_update": {
      "header_parameters": null,
      "path_parameters": null,
      "query_parameters": "DriveRepliesUpdateParametersQuery",
      "request": null,
      "response": null
    },
    "drive_revisions_delete": {
      "header_parameters": null,
      "path_parameters": null,
      "query_parameters": "DriveRevisionsDeleteParametersQuery",
      "request": null,
      "response": null
    },
    "drive_revisions_get": {
      "header_parameters": null,
      "path_parameters": null,
      "query_parameters": "DriveRevisionsGetParametersQuery",
      "request": null,
      "response": null
    },
    "drive_revisions_list": {
      "header_parameters": null,
      "path_parameters": null,
      "query_parameters": "DriveRevisionsListParametersQuery",
      "request": null,
      "response": null
    },
    "drive_revisions_update": {
      "header_parameters": null,
      "path_parameters": null,
      "query_parameters": "DriveRevisionsUpdateParametersQuery",
      "request": null,
      "response": null
    },
    "drive_teamdrives_create": {
      "header_parameters": null,
      "path_parameters": null,
      "query_parameters": "DriveTeamdrivesCreateParametersQuery",
      "request": null,
      "response": null
    },
    "drive_teamdrives_delete": {
      "header_parameters": null,
      "path_parameters": null,
      "query_parameters": "DriveTeamdrivesDeleteParametersQuery",
      "request": null,
      "response": null
    },
    "drive_teamdrives_get": {
      "header_parameters": null,
      "path_parameters": null,
      "query_parameters": "DriveTeamdrivesGetParametersQuery",
      "request": null,
      "response": null
    },
    "drive_teamdrives_list": {
      "header_parameters": null,
      "path_parameters": null,
      "query_parameters": "DriveTeamdrivesListParametersQuery",
      "request": null,
      "response": null
    },
    "drive_teamdrives_update": {
      "header_parameters": null,
      "path_parameters": null,
      "query_parameters": "DriveTeamdrivesUpdateParametersQuery",
      "request": null,
      "response": null
    }
  },
  "schema_refs": {
    "#/components/schemas/About": "About",
    "#/components/schemas/Change": "Change",
    "#/components/schemas/ChangeList": "ChangeList",
    "#/components/schemas/Channel": "Channel",
    "#/components/schemas/Comment": "Comment",
    "#/components/schemas/CommentList": "CommentList",
    "#/components/schemas/ContentRestriction": "ContentRestriction",
    "#/components/schemas/Drive": "Drive",
    "#/components/schemas/DriveList": "DriveList",
    "#/components/schemas/File": "File",
    "#/components/schemas/FileList": "FileList",
    "#/components/schemas/GeneratedIds": "GeneratedIds",
    "#/components/schemas/Label": "Label",
    "#/components/schemas/LabelField": "LabelField",
    "#/components/schemas/LabelFieldModification": "LabelFieldModification",
    "#/components/schemas/LabelList": "LabelList",
    "#/components/schemas/LabelModification": "LabelModification",
    "#/components/schemas/ModifyLabelsRequest": "ModifyLabelsRequest",
    "#/components/schemas/ModifyLabelsResponse": "ModifyLabelsResponse",
    "#/components/schemas/Permission": "Permission",
    "#/components/schemas/PermissionList": "PermissionList",
    "#/components/schemas/Reply": "Reply",
    "#/components/schemas/ReplyList": "ReplyList",
    "#/components/schemas/Revision": "Revision",
    "#/components/schemas/RevisionList": "RevisionList",
    "#/components/schemas/StartPageToken": "StartPageToken",
    "#/components/schemas/TeamDrive": "TeamDrive",
    "#/components/schemas/TeamDriveList": "TeamDriveList",
    "#/components/schemas/User": "User"
  }
}
